xmlcurses/__init__.py
xmlcurses/box.py
xmlcurses/cap.py
xmlcurses/clr.py
xmlcurses/con.py
xmlcurses/err.py
xmlcurses/fld.py
xmlcurses/tbl.py
xmlcurses/ttl.py
xmlcurses/win.py
xmlcurses-1.2.2.dist-info/DESCRIPTION.rst
xmlcurses-1.2.2.dist-info/METADATA
xmlcurses-1.2.2.dist-info/RECORD
xmlcurses-1.2.2.dist-info/WHEEL
xmlcurses-1.2.2.dist-info/metadata.json
xmlcurses-1.2.2.dist-info/top_level.txt
