Metadata-Version: 2.0
Name: xmlcurses
Version: 1.2.2
Summary: An interface for python's curses library using XML
Home-page: https://github.com/iocoder/xmlcurses
Author: Mostafa Abdelaziz
Author-email: iocoder@aol.com
License: UNKNOWN
Project-URL: Source, https://github.com/iocoder/xmlcurses
Project-URL: Bug Reports, https://github.com/iocoder/xmlcurses/issues
Keywords: development
Platform: UNKNOWN
Classifier: Development Status :: 5 - Production/Stable
Classifier: Intended Audience :: Developers
Classifier: Topic :: Software Development :: Build Tools
Classifier: License :: OSI Approved :: GNU General Public License v3 (GPLv3)
Classifier: Programming Language :: Python :: 2
Classifier: Programming Language :: Python :: 2.7
Classifier: Programming Language :: Python :: 3
Classifier: Programming Language :: Python :: 3.4
Classifier: Programming Language :: Python :: 3.5
Classifier: Programming Language :: Python :: 3.6
